"lingoqa_dataset/__init__,py"
lingoqa_dataset/lingo_judge.py
lingoqa_dataset/lingoqa_dataset.py
lingoqa_dataset-0.2.0.dist-info/METADATA
lingoqa_dataset-0.2.0.dist-info/WHEEL
lingoqa_dataset-0.2.0.dist-info/RECORD
