Metadata-Version: 2.1
Name: lingoqa-dataset
Version: 0.2.0
Summary: LingoQA dataset for pytorch
Home-page: https://github.com/hakuturu583
Author: Masaya Kataoka
Author-email: ms.kataoka@gmail.com
Requires-Python: >=3.10,<4.0
Classifier: Programming Language :: Python :: 3
Classifier: Programming Language :: Python :: 3.10
Classifier: Programming Language :: Python :: 3.11
Requires-Dist: fastparquet (>=2024.2.0,<2025.0.0)
Requires-Dist: gdown (>=5.1.0,<6.0.0)
Requires-Dist: pandas (>=2.2.1,<3.0.0)
Requires-Dist: pyarrow (>=15.0.2,<16.0.0)
Requires-Dist: torch (>=2.2.2,<3.0.0)
Requires-Dist: torchvision (>=0.17.2,<0.18.0)
Requires-Dist: tqdm (>=4.66.2,<5.0.0)
Requires-Dist: transformers (>=4.39.3,<5.0.0)
Project-URL: Repository, https://github.com/hakuturu583/lingoqa_dataset
